{
  "butterfly": {
    "de": "Schmetterling",
    "es": "mariposa",
    "fr": "papillon",
    "it": "farfalla",
    "nl": "vlinder",
    "pl": "motyl",
    "pt": "borboleta",
    "ru": "бабочка",
    "tr": "kelebek",
    "zh": "蝴蝶",
    "hi": "तितली"
  },
  "flower": {
    "de": "Blume",
    "es": "flor",
    "fr": "fleur",
    "it": "fiore",
    "nl": "bloem",
    "pl": "kwiat",
    "pt": "flor",
    "ru": "цветок",
    "tr": "çiçek",
    "zh": "花",
    "hi": "फूल"
  },
  "rabbit": {
    "de": "Kaninchen",
    "es": "conejo",
    "fr": "lapin",
    "it": "coniglio",
    "nl": "konijn",
    "pl": "królik",
    "pt": "coelho",
    "ru": "кролик",
    "tr": "tavşan",
    "zh": "兔子",
    "hi": "खरगोश"
  },
  "fox": {
    "de": "Fuchs",
    "es": "zorro",
    "fr": "renard",
    "it": "volpe",
    "nl": "vos",
    "pl": "lis",
    "pt": "raposa",
    "ru": "лиса",
    "tr": "tilki",
    "zh": "狐狸",
    "hi": "लोमड़ी"
  },
  "tree": {
    "de": "Baum",
    "es": "árbol",
    "fr": "arbre",
    "it": "albero",
    "nl": "boom",
    "pl": "drzewo",
    "pt": "árvore",
    "ru": "дерево",
    "tr": "ağaç",
    "zh": "树",
    "hi": "पेड़"
  },
  "bee": {
    "de": "Biene",
    "es": "abeja",
    "fr": "abeille",
    "it": "ape",
    "nl": "bij",
    "pl": "pszczoła",
    "pt": "abelha",
    "ru": "пчела",
    "tr": "arı",
    "zh": "蜜蜂",
    "hi": "मधुमक्खी"
  },
  "ladybug": {
    "de": "Marienkäfer",
    "es": "mariquita",
    "fr": "coccinelle",
    "it": "coccinella",
    "nl": "lieveheersbeestje",
    "pl": "biedronka",
    "pt": "joaninha",
    "ru": "божья коровка",
    "tr": "uğur böceği",
    "zh": "瓢虫",
    "hi": "लेडीबर्ड"
  },
  "penguin": {
    "de": "Pinguin",
    "es": "pingüino",
    "fr": "pingouin",
    "it": "pinguino",
    "nl": "pinguïn",
    "pl": "pingwin",
    "pt": "pinguim",
    "ru": "пингвин",
    "tr": "penguen",
    "zh": "企鹅",
    "hi": "पेंगुइन"
  },
  "polar bear": {
    "de": "Eisbär",
    "es": "oso polar",
    "fr": "ours polaire",
    "it": "orso polare",
    "nl": "ijsbeer",
    "pl": "niedźwiedź polarny",
    "pt": "urso polar",
    "ru": "белый медведь",
    "tr": "kutup ayısı",
    "zh": "北极熊",
    "hi": "ध्रुवीय भालू"
  },
  "seal": {
    "de": "Robbe",
    "es": "foca",
    "fr": "phoque",
    "it": "foca",
    "nl": "zeehond",
    "pl": "foka",
    "pt": "foca",
    "ru": "тюлень",
    "tr": "fok",
    "zh": "海豹",
    "hi": "सील"
  },
  "snowman": {
    "de": "Schneemann",
    "es": "muñeco de nieve",
    "fr": "bonhomme de neige",
    "it": "pupazzo di neve",
    "nl": "sneeuwpop",
    "pl": "bałwan",
    "pt": "boneco de neve",
    "ru": "снеговик",
    "tr": "kardan adam",
    "zh": "雪人",
    "hi": "हिममानव"
  },
  "whale": {
    "de": "Wal",
    "es": "ballena",
    "fr": "baleine",
    "it": "balena",
    "nl": "walvis",
    "pl": "wieloryb",
    "pt": "baleia",
    "ru": "кит",
    "tr": "balina",
    "zh": "鲸鱼",
    "hi": "व्हेल"
  },
  "snowflake": {
    "de": "Schneeflocke",
    "es": "copo de nieve",
    "fr": "flocon de neige",
    "it": "fiocco di neve",
    "nl": "sneeuwvlok",
    "pl": "płatek śniegu",
    "pt": "floco de neve",
    "ru": "снежинка",
    "tr": "kar tanesi",
    "zh": "雪花",
    "hi": "बर्फ का टुकड़ा"
  },
  "fish": {
    "de": "Fisch",
    "es": "pez",
    "fr": "poisson",
    "it": "pesce",
    "nl": "vis",
    "pl": "ryba",
    "pt": "peixe",
    "ru": "рыба",
    "tr": "balık",
    "zh": "鱼",
    "hi": "मछली"
  },
  "octopus": {
    "de": "Tintenfisch",
    "es": "pulpo",
    "fr": "pieuvre",
    "it": "polpo",
    "nl": "octopus",
    "pl": "ośmiornica",
    "pt": "polvo",
    "ru": "осьминог",
    "tr": "ahtapot",
    "zh": "章鱼",
    "hi": "ऑक्टोपस"
  },
  "dolphin": {
    "de": "Delfin",
    "es": "delfín",
    "fr": "dauphin",
    "it": "delfino",
    "nl": "dolfijn",
    "pl": "delfin",
    "pt": "golfinho",
    "ru": "дельфин",
    "tr": "yunus",
    "zh": "海豚",
    "hi": "डॉल्फ़िन"
  },
  "turtle": {
    "de": "Schildkröte",
    "es": "tortuga",
    "fr": "tortue",
    "it": "tartaruga",
    "nl": "schildpad",
    "pl": "żółw",
    "pt": "tartaruga",
    "ru": "черепаха",
    "tr": "kaplumbağa",
    "zh": "乌龟",
    "hi": "कछुआ"
  },
  "crab": {
    "de": "Krabbe",
    "es": "cangrejo",
    "fr": "crabe",
    "it": "granchio",
    "nl": "krab",
    "pl": "krab",
    "pt": "caranguejo",
    "ru": "краб",
    "tr": "yengeç",
    "zh": "螃蟹",
    "hi": "केकड़ा"
  },
  "shark": {
    "de": "Hai",
    "es": "tiburón",
    "fr": "requin",
    "it": "squalo",
    "nl": "haai",
    "pl": "rekin",
    "pt": "tubarão",
    "ru": "акула",
    "tr": "köpekbalığı",
    "zh": "鲨鱼",
    "hi": "शार्क"
  },
  "seahorse": {
    "de": "Seepferdchen",
    "es": "caballito de mar",
    "fr": "hippocampe",
    "it": "cavalluccio marino",
    "nl": "zeepaardje",
    "pl": "konik morski",
    "pt": "cavalo-marinho",
    "ru": "морской конёк",
    "tr": "denizatı",
    "zh": "海马",
    "hi": "समुद्री घोड़ा"
  },
  "car": {
    "de": "Auto",
    "es": "coche",
    "fr": "voiture",
    "it": "automobile",
    "nl": "auto",
    "pl": "samochód",
    "pt": "carro",
    "ru": "машина",
    "tr": "araba",
    "zh": "汽车",
    "hi": "कार"
  },
  "bus": {
    "de": "Bus",
    "es": "autobús",
    "fr": "bus",
    "it": "autobus",
    "nl": "bus",
    "pl": "autobus",
    "pt": "ônibus",
    "ru": "автобус",
    "tr": "otobüs",
    "zh": "公共汽车",
    "hi": "बस"
  },
  "house": {
    "de": "Haus",
    "es": "casa",
    "fr": "maison",
    "it": "casa",
    "nl": "huis",
    "pl": "dom",
    "pt": "casa",
    "ru": "дом",
    "tr": "ev",
    "zh": "房子",
    "hi": "घर"
  },
  "dog": {
    "de": "Hund",
    "es": "perro",
    "fr": "chien",
    "it": "cane",
    "nl": "hond",
    "pl": "pies",
    "pt": "cachorro",
    "ru": "собака",
    "tr": "köpek",
    "zh": "狗",
    "hi": "कुत्ता"
  },
  "bicycle": {
    "de": "Fahrrad",
    "es": "bicicleta",
    "fr": "vélo",
    "it": "bicicletta",
    "nl": "fiets",
    "pl": "rower",
    "pt": "bicicleta",
    "ru": "велосипед",
    "tr": "bisiklet",
    "zh": "自行车",
    "hi": "साइकिल"
  },
  "fire truck": {
    "de": "Feuerwehrauto",
    "es": "camión de bomberos",
    "fr": "camion de pompiers",
    "it": "camion dei pompieri",
    "nl": "brandweerauto",
    "pl": "wóz strażacki",
    "pt": "caminhão de bombeiros",
    "ru": "пожарная машина",
    "tr": "itfaiye aracı",
    "zh": "消防车",
    "hi": "दमकल"
  },
  "train": {
    "de": "Zug",
    "es": "tren",
    "fr": "train",
    "it": "treno",
    "nl": "trein",
    "pl": "pociąg",
    "pt": "trem",
    "ru": "поезд",
    "tr": "tren",
    "zh": "火车",
    "hi": "रेलगाड़ी"
  },
  "rocket": {
    "de": "Rakete",
    "es": "cohete",
    "fr": "fusée",
    "it": "razzo",
    "nl": "raket",
    "pl": "rakieta",
    "pt": "foguete",
    "ru": "ракета",
    "tr": "roket",
    "zh": "火箭",
    "hi": "रॉकेट"
  },
  "planet": {
    "de": "Planet",
    "es": "planeta",
    "fr": "planète",
    "it": "pianeta",
    "nl": "planeet",
    "pl": "planeta",
    "pt": "planeta",
    "ru": "планета",
    "tr": "gezegen",
    "zh": "行星",
    "hi": "ग्रह"
  },
  "astronaut": {
    "de": "Astronaut",
    "es": "astronauta",
    "fr": "astronaute",
    "it": "astronauta",
    "nl": "astronaut",
    "pl": "astronauta",
    "pt": "astronauta",
    "ru": "космонавт",
    "tr": "astronot",
    "zh": "宇航员",
    "hi": "अंतरिक्ष यात्री"
  },
  "alien": {
    "de": "Außerirdischer",
    "es": "extraterrestre",
    "fr": "extraterrestre",
    "it": "alieno",
    "nl": "buitenaards wezen",
    "pl": "kosmita",
    "pt": "alienígena",
    "ru": "инопланетянин",
    "tr": "uzaylı",
    "zh": "外星人",
    "hi": "एलियन"
  },
  "star": {
    "de": "Stern",
    "es": "estrella",
    "fr": "étoile",
    "it": "stella",
    "nl": "ster",
    "pl": "gwiazda",
    "pt": "estrela",
    "ru": "звезда",
    "tr": "yıldız",
    "zh": "星星",
    "hi": "तारा"
  },
  "moon": {
    "de": "Mond",
    "es": "luna",
    "fr": "lune",
    "it": "luna",
    "nl": "maan",
    "pl": "księżyc",
    "pt": "lua",
    "ru": "луна",
    "tr": "ay",
    "zh": "月亮",
    "hi": "चंद्रमा"
  },
  "comet": {
    "de": "Komet",
    "es": "cometa",
    "fr": "comète",
    "it": "cometa",
    "nl": "komeet",
    "pl": "kometa",
    "pt": "cometa",
    "ru": "комета",
    "tr": "kuyruklu yıldız",
    "zh": "彗星",
    "hi": "धूमकेतु"
  }
}
